wdmapper/__init__.py
wdmapper/cli.py
wdmapper/exceptions.py
wdmapper/link.py
wdmapper/property.py
wdmapper/queries.py
wdmapper/sparql.py
wdmapper/wdmapper.py
wdmapper/wikidata.py
wdmapper/format/__init__.py
wdmapper/format/base.py
wdmapper/format/beacon.py
wdmapper/format/csv.py
wdmapper/format/jskos.py
wdmapper/format/markdown.py
wdmapper/format/ntriples.py
wdmapper/format/quicks.py
wdmapper-0.0.17.dist-info/DESCRIPTION.rst
wdmapper-0.0.17.dist-info/METADATA
wdmapper-0.0.17.dist-info/RECORD
wdmapper-0.0.17.dist-info/WHEEL
wdmapper-0.0.17.dist-info/entry_points.txt
wdmapper-0.0.17.dist-info/metadata.json
wdmapper-0.0.17.dist-info/top_level.txt
