Metadata-Version: 2.0
Name: wdmapper
Version: 0.0.17
Summary: Wikidata authority file mapping tool
Home-page: http://github.com/gbv/wdmapper
Author: Jakob Voß
Author-email: jakob.voss@gbv.de
License: MIT
Download-URL: https://github.com/gbv/wdmapper/tarball/0.0.17
Keywords: wikidata,beacon,identifier
Platform: UNKNOWN
Requires-Dist: six
